<xml xmlns="https://developers.google.com/blockly/xml"><variables><variable id="z[:_]uwY}U0-g#ZzZ1HB">msg</variable></variables><block type="variables_set" id="{WX?vVp7_v4m5Xi.l.jh" x="369" y="114"><field name="VAR" id="z[:_]uwY}U0-g#ZzZ1HB">msg</field><value name="VALUE"><block type="snmp.readOids" id="Lwra99xQ]*KNQH|)3[Sf"><field name="HOST">tronV2</field><value name="OID"><block type="text" id="`GCC~__D]`b]%Q6]8XIW"><field name="TEXT">1.3.6.1.2.1.1.1.0</field></block></value></block></value><next><block type="text_print" id="WLsP@jVSZ$)/8U:ZMcZ~"><value name="TEXT"><shadow type="text" id="D^@6HgN=9QJA6!j%H`ed"><field name="TEXT">abc</field></shadow><block type="variables_get" id="~mKKD1sWjVo0z{gNr/g*"><field name="VAR" id="z[:_]uwY}U0-g#ZzZ1HB">msg</field></block></value><next><block type="abort" id="*8#!pk+Y!58TVQ,prAuH"></block></next></block></next></block></xml>